wgdi/__init__.py
wgdi/align_dotplot.py
wgdi/ancestral_karyotype.py
wgdi/ancestral_karyotype_repertoire.py
wgdi/base.py
wgdi/block_correspondence.py
wgdi/block_info.py
wgdi/block_ks.py
wgdi/circos.py
wgdi/collinearity.py
wgdi/dotplot.py
wgdi/fusion_positions_database.py
wgdi/fusions_detection.py
wgdi/karyotype.py
wgdi/karyotype_mapping.py
wgdi/ks.py
wgdi/ks_peaks.py
wgdi/ksfigure.py
wgdi/peaksfit.py
wgdi/pindex.py
wgdi/polyploidy_classification.py
wgdi/retain.py
wgdi/run.py
wgdi/run_colliearity.py
wgdi/shared_fusion.py
wgdi/trees.py
wgdi/example/__init__.py
wgdi/example/align.conf
wgdi/example/alignmenttrees.conf
wgdi/example/ancestral_karyotype.conf
wgdi/example/ancestral_karyotype_repertoire.conf
wgdi/example/blockinfo.conf
wgdi/example/blockks.conf
wgdi/example/circos.conf
wgdi/example/collinearity.conf
wgdi/example/conf.ini
wgdi/example/corr.conf
wgdi/example/dotplot.conf
wgdi/example/fusion_positions_database.conf
wgdi/example/fusions_detection.conf
wgdi/example/karyotype.conf
wgdi/example/karyotype_mapping.conf
wgdi/example/ks.conf
wgdi/example/ks_fit_result.csv
wgdi/example/ksfigure.conf
wgdi/example/kspeaks.conf
wgdi/example/peaksfit.conf
wgdi/example/pindex.conf
wgdi/example/polyploidy_classification.conf
wgdi/example/retain.conf
wgdi/example/shared_fusion.conf
wgdi-0.75.dist-info/LICENSE
wgdi-0.75.dist-info/METADATA
wgdi-0.75.dist-info/WHEEL
wgdi-0.75.dist-info/entry_points.txt
wgdi-0.75.dist-info/top_level.txt
wgdi-0.75.dist-info/zip-safe
wgdi-0.75.dist-info/RECORD
