Metadata-Version: 2.1
Name: wgdi
Version: 0.75
Summary: A user-friendly toolkit for evolutionary analyses of whole-genome duplications and ancestral karyotypes
Home-page: https://github.com/SunPengChuan/wgdi
Author: Pengchuan Sun
Author-email: sunpengchuan@gmail.com
License: BSD License
Classifier: Intended Audience :: Science/Research
Classifier: Programming Language :: Python :: 3
Classifier: License :: OSI Approved :: BSD License
Classifier: Operating System :: OS Independent
License-File: LICENSE
Requires-Dist: pandas>=1.1.0
Requires-Dist: numpy
Requires-Dist: biopython
Requires-Dist: matplotlib
Requires-Dist: scipy
Requires-Dist: tabulate
